{
  "POIs": [
    {
      "fit": [
        -0.3902944326400757,
        0.021290840581059456,
        0.14612074196338654
      ],
      "name": "yLQ2"
    }
  ],
  "method": "default",
  "params": [
    {
      "fit": [
        -0.9944697022438049,
        0.00015100205200724304,
        0.9944461584091187
      ],
      "groups": [],
      "impact_yLQ2": 0.005093371495604515,
      "name": "nlo_sys",
      "prefit": [
        -0.9999999999999999,
        0.0,
        0.9999999999999999
      ],
      "type": "Gaussian",
      "yLQ2": [
        0.02519422024488449,
        0.021290842443704605,
        0.01619747094810009
      ]
    }
  ]
}